heartflow/__init__.py
heartflow/__main__.py
heartflow-1.5.0.dist-info/METADATA
heartflow-1.5.0.dist-info/WHEEL
heartflow-1.5.0.dist-info/entry_points.txt
heartflow-1.5.0.dist-info/licenses/LICENSE
heartflow-1.5.0.dist-info/RECORD
