Metadata-Version: 2.4
Name: heartflow
Version: 1.5.0
Summary: 一个基于Python的命令行笔记应用，使用`questionary`库构建交互界面，支持笔记的增删查改和持久化存储。
Project-URL: Homepage, https://github.com/crillerium/heartflow
Project-URL: Issues, https://github.com/crillerium/heartflow/issues
Author-email: Crillerium <crillerium@outlook.com>
License-File: LICENSE
Classifier: License :: OSI Approved :: MIT License
Classifier: Operating System :: OS Independent
Classifier: Programming Language :: Python :: 3
Requires-Python: >=3.8
Requires-Dist: questionary
